be/__init__.py
be/dt_client.py
be/dt_conversation_client.py
be/dt_identities_client.py
be/rendering_blocks.py
be/routes.py
be/startup.py
be/storage.py
be/test_rendering.py
be/api/__init__.py
be/api/chat.py
be/api/dts.py
be/api/execution_node_proxy.py
be/api/ideas.py
be/api/messages.py
be/api/render.py
fe/static/app-explorer.html
fe/static/chat.html
fe/static/direct-connection.js
fe/static/dt-chat.html
fe/static/ideas.html
fe/static/index-redirect.html
fe/static/index.html
fe/static/index.html.backup
fe/static/message-renderer.css
fe/static/message-renderer.js
app.json
avyas_aurica_base_apps_chat_app-3.15.1.dist-info/METADATA
avyas_aurica_base_apps_chat_app-3.15.1.dist-info/WHEEL
avyas_aurica_base_apps_chat_app-3.15.1.dist-info/RECORD
