Metadata-Version: 2.4
Name: avyas-aurica-base-apps-chat-app
Version: 3.15.1
Summary: Aurica app: chat-app
Requires-Python: >=3.11
Requires-Dist: fastapi>=0.104.0
Requires-Dist: uvicorn>=0.24.0
